dummy.cpython-38-darwin.so
atomics-1.0.3.dist-info/RECORD
atomics-1.0.3.dist-info/WHEEL
atomics-1.0.3.dist-info/top_level.txt
atomics-1.0.3.dist-info/LICENSE.txt
atomics-1.0.3.dist-info/METADATA
atomics/__init__.py
atomics/view.py
atomics/exc.py
atomics/ctx.py
atomics/base.py
atomics/_impl/enums.py
atomics/_impl/pybuffer.py
atomics/_impl/alignment.py
atomics/_impl/__init__.py
atomics/_impl/patomic.py
atomics/_impl/exceptions.py
atomics/_impl/atomic/baseint.py
atomics/_impl/atomic/__init__.py
atomics/_impl/atomic/core.py
atomics/_impl/atomic/funcs.py
atomics/_impl/atomic/bytes.py
atomics/_impl/atomic/int.py
atomics/_impl/atomic/base.py
atomics/_impl/atomic/mixins/properties.py
atomics/_impl/atomic/mixins/cmpxchg.py
atomics/_impl/atomic/mixins/byteops.py
atomics/_impl/atomic/mixins/__init__.py
atomics/_impl/atomic/mixins/types.py
atomics/_impl/atomic/mixins/intops.py
atomics/_clib/libpatomic.0.2.2.dylib
atomics/_clib/README.txt
