Metadata-Version: 2.1
Name: atomics
Version: 1.0.3
Summary: Atomic lock-free primitives
Home-page: https://github.com/doodspav/atomics
Download-URL: https://github.com/doodspav/atomics
Author: doodspav
Author-email: doodspav@gmail.com
Project-URL: Source, https://github.com/doodspav/atomics
Project-URL: patomic, https://github.com/doodspav/patomic
Keywords: atomic,atomics,lock-free,lock free
Platform: any
Classifier: Development Status :: 5 - Production/Stable
Classifier: Intended Audience :: Developers
Classifier: Topic :: System :: Hardware :: Symmetric Multi-processing
Classifier: License :: OSI Approved :: GNU General Public License v3 (GPLv3)
Classifier: Operating System :: OS Independent
Classifier: Programming Language :: C
Classifier: Programming Language :: Python :: 3
Classifier: Programming Language :: Python :: 3 :: Only
Classifier: Programming Language :: Python :: 3.6
Classifier: Programming Language :: Python :: 3.7
Classifier: Programming Language :: Python :: 3.8
Classifier: Programming Language :: Python :: 3.9
Classifier: Programming Language :: Python :: 3.10
Classifier: Programming Language :: Python :: 3.11
Classifier: Programming Language :: Python :: Implementation :: CPython
Classifier: Programming Language :: Python :: Implementation :: PyPy
Requires-Python: <4,>=3.6
License-File: LICENSE.txt
Requires-Dist: cffi>=1.10
